MANIFEST.in
README.rst
setup.py
cpp/CMakeLists.txt
cpp/abstract.h
cpp/dict.h
cpp/fixedpoint.h
cpp/list.h
cpp/object.h
cpp/shadow.h
cpp/typy.cc
cpp/typy.cmake
cpp/typy.h
cpp/utils.h
cpp/variant.h
cpp/google/protobuf/arena.cc
cpp/google/protobuf/arena.h
cpp/google/protobuf/arenastring.h
cpp/google/protobuf/descriptor.h
cpp/google/protobuf/generated_enum_util.h
cpp/google/protobuf/generated_message_util.cc
cpp/google/protobuf/generated_message_util.h
cpp/google/protobuf/map.h
cpp/google/protobuf/map_entry_lite.h
cpp/google/protobuf/map_field_lite.h
cpp/google/protobuf/map_type_handler.h
cpp/google/protobuf/message.h
cpp/google/protobuf/message_lite.cc
cpp/google/protobuf/message_lite.h
cpp/google/protobuf/repeated_field.cc
cpp/google/protobuf/repeated_field.h
cpp/google/protobuf/wire_format_lite.cc
cpp/google/protobuf/wire_format_lite.h
cpp/google/protobuf/wire_format_lite_inl.h
cpp/google/protobuf/io/coded_stream.cc
cpp/google/protobuf/io/coded_stream.h
cpp/google/protobuf/io/coded_stream_inl.h
cpp/google/protobuf/io/zero_copy_stream.cc
cpp/google/protobuf/io/zero_copy_stream.h
cpp/google/protobuf/io/zero_copy_stream_impl_lite.cc
cpp/google/protobuf/io/zero_copy_stream_impl_lite.h
cpp/google/protobuf/stubs/atomic_sequence_num.h
cpp/google/protobuf/stubs/atomicops.h
cpp/google/protobuf/stubs/atomicops_internals_atomicword_compat.h
cpp/google/protobuf/stubs/atomicops_internals_macosx.h
cpp/google/protobuf/stubs/atomicops_internals_x86_gcc.cc
cpp/google/protobuf/stubs/atomicops_internals_x86_gcc.h
cpp/google/protobuf/stubs/atomicops_internals_x86_msvc.cc
cpp/google/protobuf/stubs/atomicops_internals_x86_msvc.h
cpp/google/protobuf/stubs/callback.h
cpp/google/protobuf/stubs/casts.h
cpp/google/protobuf/stubs/common.cc
cpp/google/protobuf/stubs/common.h
cpp/google/protobuf/stubs/fastmem.h
cpp/google/protobuf/stubs/hash.h
cpp/google/protobuf/stubs/int128.cc
cpp/google/protobuf/stubs/int128.h
cpp/google/protobuf/stubs/logging.h
cpp/google/protobuf/stubs/macros.h
typyd.egg-info/PKG-INFO
typyd.egg-info/SOURCES.txt
typyd.egg-info/dependency_links.txt
typyd.egg-info/top_level.txt