Metadata-Version: 1.1
Name: typyd
Version: 0.0.1
Summary: A single-file database storages key-value pairs.
Home-page: http://github.com/ibelie/typy
Author: joungtao
Author-email: joungtao@gmail.com
License: MIT License
Keywords: noSql,key-value,database,typy
Platform: UNKNOWN
Classifier: Development Status :: 3 - Alpha
Classifier: Environment :: Console
Classifier: Natural Language :: English
Classifier: Operating System :: OS Independent
Classifier: License :: OSI Approved :: MIT License
Classifier: Intended Audience :: Developers
Classifier: Intended Audience :: Science/Research
Classifier: Intended Audience :: Education
Classifier: Topic :: Software Development :: Libraries
Classifier: Programming Language :: Python :: 2.7
Classifier: Programming Language :: Python :: 3.5
